taskcat/.DS_Store
taskcat/__init__.py
taskcat/_amiupdater.py
taskcat/_cfn/__init__.py
taskcat/_cfn/_log_stack_events.py
taskcat/_cfn/stack.py
taskcat/_cfn/stack_url_helper.py
taskcat/_cfn/template.py
taskcat/_cfn/threaded.py
taskcat/_cfn_lint.py
taskcat/_cli.py
taskcat/_cli_core.py
taskcat/_cli_modules/__init__.py
taskcat/_cli_modules/config.py
taskcat/_cli_modules/delete.py
taskcat/_cli_modules/deploy.py
taskcat/_cli_modules/generate_config.py
taskcat/_cli_modules/generate_iam_policy.py
taskcat/_cli_modules/lint.py
taskcat/_cli_modules/list.py
taskcat/_cli_modules/package.py
taskcat/_cli_modules/package_single.py
taskcat/_cli_modules/test.py
taskcat/_cli_modules/update_ami.py
taskcat/_cli_modules/upload.py
taskcat/_client_factory.py
taskcat/_common_utils.py
taskcat/_config.py
taskcat/_dataclasses.py
taskcat/_generate_reports.py
taskcat/_lambda_build.py
taskcat/_legacy_config.py
taskcat/_logger.py
taskcat/_name_generator.py
taskcat/_s3_stage.py
taskcat/_s3_sync.py
taskcat/_template_params.py
taskcat/_tui.py
taskcat/cfg/amiupdater.cfg.yml
taskcat/cfg/animals.txt
taskcat/cfg/cfn_resource_iam_policy.json
taskcat/cfg/config_schema.json
taskcat/cfg/descriptors.txt
taskcat/exceptions.py
taskcat/iam_policy/__init__.py
taskcat/iam_policy/policy.py
taskcat/iam_policy/tools.py
taskcat/local_zones.py
taskcat/project_config/__init__.py
taskcat/project_config/config.py
taskcat/project_config/tools.py
taskcat/project_templates/quickstart/README.md.jinja
taskcat/project_templates/quickstart/ci/debug-input.json.jinja
taskcat/project_templates/quickstart/ci/taskcat-autobucket-json.yml.jinja
taskcat/project_templates/quickstart/ci/taskcat-autobucket.yml.jinja
taskcat/project_templates/quickstart/ci/taskcat.yml.jinja
taskcat/project_templates/quickstart/scripts/scripts_userdata.sh.jinja
taskcat/project_templates/quickstart/templates/debug-yaml.template.jinja
taskcat/project_templates/quickstart/templates/debug.template.jinja
taskcat/regions_to_partitions.py
taskcat-0.9.56.dist-info/LICENSE.txt
taskcat-0.9.56.dist-info/METADATA
taskcat-0.9.56.dist-info/WHEEL
taskcat-0.9.56.dist-info/entry_points.txt
taskcat-0.9.56.dist-info/RECORD
