Metadata-Version: 2.3
Name: taskcat
Version: 0.9.56
Summary: An OpenSource Cloudformation Deployment Framework
Author: Andrew Glenn
Requires-Python: >=3.8.0,<4.0
Classifier: Programming Language :: Python :: 3
Classifier: Programming Language :: Python :: 3.8
Classifier: Programming Language :: Python :: 3.9
Classifier: Programming Language :: Python :: 3.10
Classifier: Programming Language :: Python :: 3.11
Classifier: Programming Language :: Python :: 3.12
Classifier: Programming Language :: Python :: 3.13
Requires-Dist: GitPython (>=3.1.43)
Requires-Dist: PyYAML (>=6.0,<7.0)
Requires-Dist: boto3 (>=1.9.21,<2.0)
Requires-Dist: botocore (>=1.12.21,<2.0)
Requires-Dist: cfn_lint (>=0.78.1,<2.0)
Requires-Dist: dataclasses-jsonschema (>=2.9.0,<2.15.2)
Requires-Dist: docker (>=7.0,<8.0)
Requires-Dist: dulwich (>=0.19,<1.0)
Requires-Dist: jinja2 (>=3.1.1,<4.0)
Requires-Dist: jsonschema (>=3.0,<4.0)
Requires-Dist: markupsafe (==2.0.1)
Requires-Dist: pathspec (==0.10.3)
Requires-Dist: pip
Requires-Dist: reprint
Requires-Dist: requests (>=2.31.0)
Requires-Dist: setuptools (>=40.4.3)
Requires-Dist: tabulate (>=0.8.2,<1.0)
Requires-Dist: urllib3 (<2)
Requires-Dist: yattag (>=1.10.0,<2.0)
